{"query_name":"03-bridges-waterworks","query_signature":"a2a038a0c4e040a3744ec1d58f52579e1a140831","tile_path":"110","payload":{"version":0.6,"generator":"Overpass API 0.7.62.11 87bfad18","osm3s":{"timestamp_osm_base":"2026-07-14T20:43:13Z","copyright":"The data included in this document is from www.openstreetmap.org. The data is made available under ODbL."},"elements":[{"type":"way","id":60231048,"nodes":[748311053,748311052],"tags":{"bridge":"yes","highway":"track","layer":"1"}},{"type":"way","id":60231257,"nodes":[748318359,748318361],"tags":{"bridge":"yes","highway":"unclassified","lane_markings":"no","lanes":"1","layer":"1","lit":"no","name":"Almsick","shoulder":"no","sidewalk":"no","width":"3","zone:traffic":"DE:rural"}},{"type":"way","id":60231607,"nodes":[748327580,748327582],"tags":{"bridge":"yes","highway":"track","railway":"razed","razed:railway":"rail"}},{"type":"way","id":1011090501,"nodes":[348103978,9328329801],"tags":{"bridge":"yes","highway":"unclassified","layer":"1","name":"Düster Stegge","source":"NRW Geobasis ALK"}},{"type":"way","id":1021522857,"nodes":[4694412178,9421480933],"tags":{"bicycle":"yes","bridge":"yes","foot":"yes","highway":"track","horse":"yes","layer":"1","source":"NRW Geobasis ALK","surface":"asphalt"}},{"type":"node","id":348103978,"lat":52.0085011,"lon":6.9690991},{"type":"node","id":9328329801,"lat":52.008422,"lon":6.9690697},{"type":"node","id":748318359,"lat":52.0236508,"lon":6.9569398},{"type":"node","id":748318361,"lat":52.0236765,"lon":6.9568431},{"type":"node","id":748311052,"lat":52.0135804,"lon":6.9850376},{"type":"node","id":748311053,"lat":52.0135823,"lon":6.9850029},{"type":"node","id":748327580,"lat":52.027313,"lon":6.9831414},{"type":"node","id":748327582,"lat":52.0272765,"lon":6.9830957},{"type":"node","id":4694412178,"lat":52.0310069,"lon":7.0146248},{"type":"node","id":9421480933,"lat":52.0309367,"lon":7.0145908}]}}
