{"query_name":"03-bridges-waterworks","query_signature":"9da10cbbe48740a07ddb115cf3673f4631d87337","tile_path":"127","payload":{"version":0.6,"generator":"Overpass API 0.7.62.11 87bfad18","osm3s":{"timestamp_osm_base":"2026-07-14T20:47:15Z","copyright":"The data included in this document is from www.openstreetmap.org. The data is made available under ODbL."},"elements":[{"type":"node","id":872473990,"lat":52.0650866,"lon":7.0964265,"tags":{"waterway":"weir"}},{"type":"way","id":5053046,"nodes":[33979153,17689782],"tags":{"bridge":"yes","highway":"motorway","lanes":"2","layer":"1","lit":"no","loc_name":"Ostfriesenspieß","maxspeed":"none","note:name":"Der reg_name, sowie ggf. der loc_name sind dem zugehörigen Wikipediaartikel entnommen.","oneway":"yes","ref":"A 31","reg_name":"Emslandautobahn","source:lit":"http://www.autobahn-bilder.de","surface":"asphalt"}},{"type":"way","id":5110547,"nodes":[35095272,35095271],"tags":{"bridge":"yes","highway":"motorway","lanes":"2","layer":"1","lit":"no","loc_name":"Ostfriesenspieß","maxspeed":"none","note:name":"Der reg_name, sowie ggf. der loc_name sind dem zugehörigen Wikipediaartikel entnommen.","oneway":"yes","ref":"A 31","reg_name":"Emslandautobahn","source:lit":"http://www.autobahn-bilder.de","surface":"asphalt"}},{"type":"way","id":28967691,"nodes":[318520367,318520349],"tags":{"bridge":"yes","destination:lanes":"Gescher;Coesfeld|Gesher;Coesfeld|Legden;Ahaus;Vreden;Stadtlohn","destination:ref:lanes":"A 31|A 31|B 474","highway":"motorway","lanes":"3","layer":"1","lit":"no","loc_name":"Ostfriesenspieß","maxspeed":"none","note:name":"Der reg_name, sowie ggf. der loc_name sind dem zugehörigen Wikipediaartikel entnommen.","oneway":"yes","ref":"A 31","reg_name":"Emslandautobahn","source:lit":"http://www.autobahn-bilder.de","surface":"asphalt","turn:lanes":"none|none|slight_right"}},{"type":"way","id":28967695,"nodes":[318520293,318520294],"tags":{"bridge":"yes","destination:lanes":"||Legden;Ahaus;Vreden;Rosendahl","destination:ref:lanes":"A 31|A 31|B 474","highway":"motorway","lanes":"3","layer":"1","lit":"no","loc_name":"Ostfriesenspieß","maxspeed":"none","note:name":"Der reg_name, sowie ggf. der loc_name sind dem zugehörigen Wikipediaartikel entnommen.","oneway":"yes","ref":"A 31","reg_name":"Emslandautobahn","source:lit":"http://www.autobahn-bilder.de","surface":"asphalt","turn:lanes":"none|none|slight_right"}},{"type":"way","id":32208473,"nodes":[361188521,361188522],"tags":{"bridge":"yes","highway":"motorway","lanes":"2","layer":"1","lit":"no","loc_name":"Ostfriesenspieß","maxspeed":"none","note:name":"Der reg_name, sowie ggf. der loc_name sind dem zugehörigen Wikipediaartikel entnommen.","oneway":"yes","ref":"A 31","reg_name":"Emslandautobahn","source:lit":"http://www.autobahn-bilder.de","surface":"asphalt"}},{"type":"way","id":32208474,"nodes":[361188523,361179625],"tags":{"bridge":"yes","highway":"motorway","lanes":"2","layer":"1","lit":"no","loc_name":"Ostfriesenspieß","maxspeed":"none","note:name":"Der reg_name, sowie ggf. der loc_name sind dem zugehörigen Wikipediaartikel entnommen.","oneway":"yes","ref":"A 31","reg_name":"Emslandautobahn","source:lit":"http://www.autobahn-bilder.de","surface":"asphalt"}},{"type":"way","id":37846426,"nodes":[443842557,443842558],"tags":{"bridge":"yes","highway":"unclassified","layer":"1","lit":"no"}},{"type":"way","id":60232542,"nodes":[418396469,2576129024,748367107],"tags":{"bridge":"yes","highway":"unclassified","layer":"1"}},{"type":"way","id":60232800,"nodes":[748376554,748376552],"tags":{"bridge":"yes","highway":"primary","lanes":"2","lanes:backward":"1","lanes:forward":"1","layer":"1","maxspeed":"100","ref":"B 474","surface":"asphalt"}},{"type":"way","id":94188581,"nodes":[1094755892,1939430447,1094755689],"tags":{"bridge":"yes","highway":"secondary","lanes":"2","lanes:backward":"1","lanes:forward":"1","layer":"1","maxspeed":"100","ref":"L 574","sidewalk:left":"no","sidewalk:right":"separate"}},{"type":"way","id":94188587,"nodes":[1094755831,848011184],"tags":{"bicycle":"designated","bridge":"yes","foot":"designated","highway":"path","layer":"1","segregated":"no","surface":"asphalt","width":"1.5"}},{"type":"way","id":94188592,"nodes":[319815036,319815056],"tags":{"bridge":"yes","cycleway:both":"no","highway":"tertiary","lane_markings":"no","layer":"1","lit":"no","ref":"K 61","shoulder":"no","sidewalk":"no","source":"http://wiki.openstreetmap.org/wiki/Import/Catalogue/Strassen_NRW","strassen-nrw:abs":"3908019O3908016O","surface":"asphalt","zone:traffic":"DE:rural"}},{"type":"way","id":94188616,"nodes":[319815186,319815194],"tags":{"bridge":"yes","cycleway:both":"no","highway":"tertiary","lane_markings":"no","layer":"1","lit":"no","ref":"K 61","shoulder":"no","sidewalk":"no","source":"http://wiki.openstreetmap.org/wiki/Import/Catalogue/Strassen_NRW","strassen-nrw:abs":"3908019O3908016O","surface":"asphalt","zone:traffic":"DE:rural"}},{"type":"way","id":161528967,"nodes":[1735054760,35095271],"tags":{"bridge":"yes","destination:ref":"A 31","highway":"motorway_link","lanes":"1","layer":"1","oneway":"yes","surface":"asphalt"}},{"type":"way","id":177719276,"nodes":[1774346918,1774346917],"tags":{"bicycle":"designated","bridge":"yes","foot":"designated","highway":"cycleway","is_sidepath":"yes","layer":"1","surface":"asphalt"}},{"type":"way","id":182061248,"nodes":[1924037187,426873274],"tags":{"bridge":"yes","highway":"unclassified","layer":"1","name":"Wehr"}},{"type":"way","id":768272922,"nodes":[7172854885,7172854887,7172854888],"tags":{"bridge":"yes","highway":"service","layer":"1"}},{"type":"way","id":780236944,"nodes":[7285316814,4249956970],"tags":{"bridge":"yes","highway":"unclassified","layer":"1","name":"Neue Mühle"}},{"type":"way","id":1447454656,"nodes":[3165309115,418396442],"tags":{"bridge":"yes","highway":"unclassified","layer":"1"}},{"type":"way","id":1447454658,"nodes":[13280412524,13280412525],"tags":{"bridge":"yes","highway":"track","layer":"1"}},{"type":"node","id":17689782,"lat":52.0510031,"lon":7.0624548},{"type":"node","id":33979153,"lat":52.0507829,"lon":7.0624094},{"type":"node","id":35095271,"lat":52.0508384,"lon":7.0622039},{"type":"node","id":35095272,"lat":52.0510952,"lon":7.0622668},{"type":"node","id":361179625,"lat":52.0469071,"lon":7.0616518},{"type":"node","id":361188521,"lat":52.0468592,"lon":7.0618274},{"type":"node","id":361188522,"lat":52.0470549,"lon":7.0618453},{"type":"node","id":361188523,"lat":52.0471098,"lon":7.0616745},{"type":"node","id":1735054760,"lat":52.0511058,"lon":7.0622065},{"type":"node","id":318520293,"lat":52.0529492,"lon":7.0629252},{"type":"node","id":318520294,"lat":52.0532191,"lon":7.0629948},{"type":"node","id":318520349,"lat":52.0530808,"lon":7.0627294},{"type":"node","id":318520367,"lat":52.053316,"lon":7.062796},{"type":"node","id":443842557,"lat":52.0683128,"lon":7.0698797},{"type":"node","id":443842558,"lat":52.0681614,"lon":7.0708128},{"type":"node","id":748376552,"lat":52.0463857,"lon":7.0802677},{"type":"node","id":748376554,"lat":52.0464845,"lon":7.0800282},{"type":"node","id":1774346917,"lat":52.0464065,"lon":7.0803885},{"type":"node","id":1774346918,"lat":52.0465375,"lon":7.0800647},{"type":"node","id":4249956970,"lat":52.0432415,"lon":7.094016},{"type":"node","id":7172854885,"lat":52.0413828,"lon":7.0971821},{"type":"node","id":7172854887,"lat":52.041367,"lon":7.0971404},{"type":"node","id":7172854888,"lat":52.0413463,"lon":7.0970876},{"type":"node","id":7285316814,"lat":52.043306,"lon":7.0940678},{"type":"node","id":418396469,"lat":52.0526906,"lon":7.0889426},{"type":"node","id":748367107,"lat":52.0527465,"lon":7.0887897},{"type":"node","id":2576129024,"lat":52.0527253,"lon":7.0888571},{"type":"node","id":418396442,"lat":52.064951,"lon":7.0964755},{"type":"node","id":3165309115,"lat":52.0649534,"lon":7.0962517},{"type":"node","id":426873274,"lat":52.0702396,"lon":7.0953684},{"type":"node","id":1924037187,"lat":52.0702943,"lon":7.0955849},{"type":"node","id":13280412524,"lat":52.0656164,"lon":7.0967358},{"type":"node","id":13280412525,"lat":52.0656474,"lon":7.0965323},{"type":"node","id":319815036,"lat":52.069585,"lon":7.0990339},{"type":"node","id":319815056,"lat":52.0693315,"lon":7.0989197},{"type":"node","id":319815186,"lat":52.0653533,"lon":7.1031927},{"type":"node","id":319815194,"lat":52.0653869,"lon":7.1033613},{"type":"node","id":848011184,"lat":52.0617077,"lon":7.1065023},{"type":"node","id":1094755689,"lat":52.061714,"lon":7.1065896},{"type":"node","id":1094755831,"lat":52.062007,"lon":7.1065919},{"type":"node","id":1094755892,"lat":52.0619885,"lon":7.1066762},{"type":"node","id":1939430447,"lat":52.0618872,"lon":7.1066415}]}}
