{"query_name":"03-bridges-waterworks","query_signature":"a72cc3e2adf0e5799938bec9abbb1adbaadcd1b3","tile_path":"225","payload":{"version":0.6,"generator":"Overpass API 0.7.62.11 87bfad18","osm3s":{"timestamp_osm_base":"2026-07-14T21:11:53Z","copyright":"The data included in this document is from www.openstreetmap.org. The data is made available under ODbL."},"elements":[{"type":"node","id":6961487176,"lat":52.2982561,"lon":5.969017,"tags":{"waterway":"weir"}},{"type":"node","id":6967252856,"lat":52.2906092,"lon":5.9645989,"tags":{"waterway":"weir"}},{"type":"node","id":6967252857,"lat":52.2919416,"lon":5.9620256,"tags":{"waterway":"weir"}},{"type":"node","id":6967305628,"lat":52.287268,"lon":5.9151641,"tags":{"waterway":"weir"}},{"type":"node","id":8335829470,"lat":52.2905049,"lon":5.9661971,"tags":{"waterway":"weir"}},{"type":"way","id":198901578,"nodes":[2089764654,2089764678],"tags":{"bridge":"yes","highway":"footway","layer":"1"}},{"type":"way","id":198902059,"nodes":[12552358305,13374658667,13374658668,2089764654],"tags":{"bridge":"yes","highway":"footway","layer":"1"}},{"type":"way","id":267555199,"nodes":[2191575081,2191575091],"tags":{"bridge":"yes","highway":"footway","layer":"1"}},{"type":"way","id":284686535,"nodes":[2884046104,2884046162,2884046152,2884046146,2884046134,2884046108,2884046118,2884043700,2884046104],"tags":{"building":"industrial","heritage":"8","man_made":"watermill","name":"Cannenburger Molen","ref:bag":"0232100000015092","source":"BAG","source:date":"2014-05-26","start_date":"1940","wikidata":"Q2098254","wikipedia":"nl:Cannenburger Molen"}},{"type":"way","id":325977458,"nodes":[3325882090,3325882091],"tags":{"bridge":"yes","highway":"track","layer":"1","opening_hours":"sunrise-sunset","operator":"Kroondomein het Loo","seasonal":"no","surface":"compacted"}},{"type":"way","id":345338880,"nodes":[3520325715,3520325716],"tags":{"bicycle":"permissive","bridge":"yes","foot":"permissive","highway":"path","layer":"1","motor_vehicle":"no","name":"Kersendijkje","segregated":"no","smoothness":"good","surface":"wood"}},{"type":"way","id":345338885,"nodes":[3520325718,3520325719],"tags":{"bicycle":"permissive","bridge":"yes","foot":"permissive","highway":"path","layer":"1","motor_vehicle":"no","name":"Kersendijkje","segregated":"no","smoothness":"good","surface":"wood"}},{"type":"way","id":483463874,"nodes":[4762006257,4762006256],"tags":{"bridge":"yes","highway":"path","layer":"1","lit":"yes","smoothness":"good","surface":"wood"}},{"type":"way","id":743649638,"nodes":[6960126837,6960126838],"tags":{"bridge":"yes","highway":"track","layer":"1","tracktype":"grade4"}},{"type":"way","id":743685405,"nodes":[2089754872,6960428056],"tags":{"bridge":"yes","highway":"path","layer":"1"}},{"type":"way","id":743685406,"nodes":[6960428060,46039658],"tags":{"bridge":"yes","highway":"service","layer":"1","name":"Maarten van Rossumplein","service":"driveway"}},{"type":"way","id":744432838,"nodes":[6967305630,6960372384,6967305629],"tags":{"waterway":"dam"}},{"type":"way","id":744432839,"nodes":[6967305631,6967305632],"tags":{"bridge":"aqueduct","layer":"1","name":"Geelmolense Beek","waterway":"stream"}},{"type":"way","id":779729034,"nodes":[7281103738,7281103739],"tags":{"access:conditional":"no @ (sunset-sunrise)","bicycle":"permissive","bicycle:conditional":"no @ (sunset-sunrise)","bridge":"yes","foot":"permissive","foot:conditional":"no @ (sunset-sunrise)","highway":"track","layer":"1","motor_vehicle":"no","opening_hours":"sunrise-sunset","operator":"Kroondomein het Loo","seasonal":"no"}},{"type":"way","id":779729036,"nodes":[7281103743,7281103744],"tags":{"access:conditional":"no @ (sunset-sunrise)","bicycle":"permissive","bicycle:conditional":"no @ (sunset-sunrise)","bridge":"yes","foot":"permissive","foot:conditional":"no @ (sunset-sunrise)","highway":"track","layer":"1","motor_vehicle":"no","opening_hours":"sunrise-sunset","operator":"Kroondomein het Loo","seasonal":"no"}},{"type":"way","id":804352554,"nodes":[7523546841,7523546840],"tags":{"bridge":"yes","highway":"track","layer":"1","name":"Hattumseweg","smoothness":"good","surface":"wood"}},{"type":"way","id":804352556,"nodes":[46046583,7523546843],"tags":{"bridge":"yes","highway":"cycleway","layer":"1"}},{"type":"way","id":863312094,"nodes":[8042274645,8042274646],"tags":{"bridge":"yes","highway":"path","layer":"1"}},{"type":"way","id":896074744,"nodes":[3494545947,8329524231],"tags":{"bridge":"yes","highway":"track","layer":"1","note":"This track seems to be very inacurate","tracktype":"grade4"}},{"type":"way","id":896767406,"nodes":[8335829458,2089754898],"tags":{"bridge":"yes","highway":"footway","layer":"1","wikidata":"Q17596581"}},{"type":"way","id":898084824,"nodes":[8346197381,8346197380,8346197379,8346197378,8398008217,8398008216,8398008215],"tags":{"waterway":"dam"}},{"type":"way","id":938742063,"nodes":[8696419402,8696419401],"tags":{"access":"agricultural","bridge":"yes","highway":"track","layer":"1"}},{"type":"way","id":940446773,"nodes":[8709857823,8709857822],"tags":{"bridge":"yes","highway":"path","layer":"1"}},{"type":"way","id":940446817,"nodes":[8709874912,8709874911],"tags":{"bridge":"yes","highway":"service","layer":"1","name":"Maarten van Rossumplein","service":"parking_aisle","surface":"paving_stones"}},{"type":"way","id":940569951,"nodes":[8710851687,6967252853,8710851686],"tags":{"waterway":"weir"}},{"type":"way","id":942216728,"nodes":[3325882100,8725110882],"tags":{"access:conditional":"no @ (sunset-sunrise)","bicycle":"permissive","bicycle:conditional":"no @ (sunset-sunrise)","bridge":"yes","foot":"permissive","foot:conditional":"no @ (sunset-sunrise)","highway":"track","layer":"1","motor_vehicle":"no","opening_hours":"sunrise-sunset","operator":"Kroondomein het Loo","seasonal":"no","tracktype":"grade5"}},{"type":"way","id":1080731490,"nodes":[9905757923,9905748368],"tags":{"bridge":"yes","highway":"footway","layer":"1","traffic_sign":"NL:G07"}},{"type":"way","id":1091587817,"nodes":[9997283242,9997283243],"tags":{"bridge":"yes","highway":"service","layer":"1"}},{"type":"way","id":1356264845,"nodes":[8709875615,12552358306,13374658669,2089764654],"tags":{"bridge":"yes","highway":"footway","layer":"1"}},{"type":"way","id":1367013636,"nodes":[12659649345,12659649346],"tags":{"bridge":"yes","highway":"footway","layer":"1"}},{"type":"way","id":1418673272,"nodes":[13037334975,13037334974],"tags":{"bridge":"yes","highway":"footway","layer":"1"}},{"type":"node","id":3325882090,"lat":52.284086,"lon":5.9174159},{"type":"node","id":3325882091,"lat":52.2841165,"lon":5.9174345},{"type":"node","id":3325882100,"lat":52.2847942,"lon":5.9167937},{"type":"node","id":6960126837,"lat":52.2873171,"lon":5.9157735},{"type":"node","id":6960126838,"lat":52.287358,"lon":5.9157423},{"type":"node","id":7281103738,"lat":52.2854546,"lon":5.9114403},{"type":"node","id":7281103739,"lat":52.2855186,"lon":5.9114723},{"type":"node","id":7281103743,"lat":52.2861758,"lon":5.9136342},{"type":"node","id":7281103744,"lat":52.2861989,"lon":5.9138078},{"type":"node","id":8725110882,"lat":52.2848253,"lon":5.9168049},{"type":"node","id":8042274645,"lat":52.2838335,"lon":5.9208122},{"type":"node","id":8042274646,"lat":52.2837844,"lon":5.9208033},{"type":"node","id":7523546840,"lat":52.2876007,"lon":5.9279364},{"type":"node","id":7523546841,"lat":52.2875565,"lon":5.9279292},{"type":"node","id":6967305631,"lat":52.2866504,"lon":5.9450218},{"type":"node","id":6967305632,"lat":52.2866568,"lon":5.9450522},{"type":"node","id":9905748368,"lat":52.2849074,"lon":5.9709291},{"type":"node","id":9905757923,"lat":52.2850155,"lon":5.970931},{"type":"node","id":6960372384,"lat":52.2891391,"lon":5.9148019},{"type":"node","id":6967305629,"lat":52.289146,"lon":5.9148434},{"type":"node","id":6967305630,"lat":52.2891322,"lon":5.914751},{"type":"node","id":3494545947,"lat":52.2879532,"lon":5.9220204},{"type":"node","id":8329524231,"lat":52.287999,"lon":5.9220356},{"type":"node","id":8346197378,"lat":52.2889366,"lon":5.9483659},{"type":"node","id":8346197379,"lat":52.2889732,"lon":5.948123},{"type":"node","id":8346197380,"lat":52.2887309,"lon":5.9466864},{"type":"node","id":8346197381,"lat":52.2887171,"lon":5.9466633},{"type":"node","id":8398008215,"lat":52.2890981,"lon":5.9493468},{"type":"node","id":8398008216,"lat":52.289078,"lon":5.94931},{"type":"node","id":8398008217,"lat":52.2889504,"lon":5.948463},{"type":"node","id":9997283242,"lat":52.2902553,"lon":5.946503},{"type":"node","id":9997283243,"lat":52.2902073,"lon":5.9465291},{"type":"node","id":2089754872,"lat":52.2918379,"lon":5.9617995},{"type":"node","id":2089764654,"lat":52.2919083,"lon":5.9605279},{"type":"node","id":2089764678,"lat":52.2920031,"lon":5.9604588},{"type":"node","id":2191575081,"lat":52.2926558,"lon":5.9630879},{"type":"node","id":2191575091,"lat":52.2926654,"lon":5.9631866},{"type":"node","id":6960428056,"lat":52.2918002,"lon":5.9618704},{"type":"node","id":8709875615,"lat":52.2917825,"lon":5.9605397},{"type":"node","id":12552358305,"lat":52.2918397,"lon":5.9606514},{"type":"node","id":12552358306,"lat":52.2918195,"lon":5.9605427},{"type":"node","id":13374658667,"lat":52.2918654,"lon":5.9605989},{"type":"node","id":13374658668,"lat":52.2918884,"lon":5.9605618},{"type":"node","id":13374658669,"lat":52.2918596,"lon":5.9605384},{"type":"node","id":8696419401,"lat":52.2969097,"lon":5.9548779},{"type":"node","id":8696419402,"lat":52.2968759,"lon":5.9549029},{"type":"node","id":46039658,"lat":52.2905928,"lon":5.9650141},{"type":"node","id":2089754898,"lat":52.2920532,"lon":5.965202},{"type":"node","id":2884043700,"lat":52.2926784,"lon":5.9670061},{"type":"node","id":2884046104,"lat":52.2926901,"lon":5.9668834},{"type":"node","id":2884046108,"lat":52.2926988,"lon":5.9672731},{"type":"node","id":2884046118,"lat":52.2927232,"lon":5.9670175},{"type":"node","id":2884046134,"lat":52.2927664,"lon":5.9672903},{"type":"node","id":2884046146,"lat":52.2927908,"lon":5.9670354},{"type":"node","id":2884046152,"lat":52.2928054,"lon":5.9670391},{"type":"node","id":2884046162,"lat":52.2928172,"lon":5.9669157},{"type":"node","id":3520325715,"lat":52.2904461,"lon":5.9662634},{"type":"node","id":3520325716,"lat":52.290511,"lon":5.9662758},{"type":"node","id":3520325718,"lat":52.2926761,"lon":5.9667439},{"type":"node","id":3520325719,"lat":52.292711,"lon":5.966753},{"type":"node","id":6960428060,"lat":52.2905507,"lon":5.9650079},{"type":"node","id":8335829458,"lat":52.2918226,"lon":5.9651735},{"type":"node","id":8709857822,"lat":52.2906846,"lon":5.9645594},{"type":"node","id":8709857823,"lat":52.2906886,"lon":5.9644563},{"type":"node","id":8709874911,"lat":52.2908258,"lon":5.9654199},{"type":"node","id":8709874912,"lat":52.2908282,"lon":5.9653462},{"type":"node","id":12659649345,"lat":52.290697,"lon":5.9638194},{"type":"node","id":12659649346,"lat":52.2906304,"lon":5.9638047},{"type":"node","id":46046583,"lat":52.2921973,"lon":5.9709651},{"type":"node","id":4762006256,"lat":52.2910831,"lon":5.9718679},{"type":"node","id":4762006257,"lat":52.2911186,"lon":5.9718381},{"type":"node","id":6967252853,"lat":52.2918567,"lon":5.9749957},{"type":"node","id":7523546843,"lat":52.2922421,"lon":5.9709764},{"type":"node","id":8710851686,"lat":52.2918565,"lon":5.974982},{"type":"node","id":8710851687,"lat":52.2918562,"lon":5.9750065},{"type":"node","id":13037334974,"lat":52.2920849,"lon":5.9725558},{"type":"node","id":13037334975,"lat":52.2920052,"lon":5.9725311}]}}
