{"query_name":"03-bridges-waterworks","query_signature":"4019c21f566ba2e23171c1abf05c920de5fe40ea","tile_path":"31","payload":{"version":0.6,"generator":"Overpass API 0.7.62.11 87bfad18","osm3s":{"timestamp_osm_base":"2026-07-14T20:25:00Z","copyright":"The data included in this document is from www.openstreetmap.org. The data is made available under ODbL."},"elements":[{"type":"way","id":25670777,"nodes":[279851608,279851617],"tags":{"bridge":"yes","highway":"trunk","lanes":"4","lanes:backward":"2","lanes:forward":"2","layer":"1","maxspeed":"100","motorroad":"yes","note":"2+1-System","ref":"B 67","turn:lanes:forward":"|slight_right"}},{"type":"way","id":25671212,"nodes":[102862426,102862434],"tags":{"bridge":"yes","highway":"trunk","lanes":"4","lanes:backward":"2","lanes:forward":"2","layer":"1","maxspeed":"100","motorroad":"yes","note":"2+1-System","ref":"B 67"}},{"type":"way","id":32139310,"nodes":[360797277,360797275],"tags":{"bridge":"yes","cycleway:both":"no","highway":"unclassified","lanes":"1","layer":"1"}},{"type":"way","id":154801351,"nodes":[1672751916,295658847],"tags":{"access":"agricultural","bicycle":"yes","bridge":"yes","foot":"yes","highway":"track","layer":"1","motorcar":"agricultural","motorcycle":"no","surface":"paved","tracktype":"grade1","width":"3"}},{"type":"way","id":154801432,"nodes":[1672751713,1672751731],"tags":{"bicycle":"yes","bridge":"yes","foot":"yes","highway":"track","layer":"1","mtb:scale":"0","mtb:type":"crosscountry","surface":"gravel","tracktype":"grade2","width":"3"}},{"type":"way","id":154801440,"nodes":[1672752049,1672752061],"tags":{"bridge":"yes","electrified":"no","gauge":"1435","layer":"1","maxspeed":"100","passenger_lines":"1","railway":"rail","railway:pzb":"yes","ref":"2273","tracks":"1","usage":"branch"}},{"type":"way","id":154804061,"nodes":[1672769735,1672769734],"tags":{"bridge":"yes","class:bicycle":"-2","highway":"secondary","lanes":"2","lanes:backward":"1","lanes:forward":"1","layer":"1","maxspeed":"100","name":"Stevede","ref":"L 600","source":"http://wiki.openstreetmap.org/wiki/Import/Catalogue/Strassen_NRW"}},{"type":"way","id":154806117,"nodes":[1672794063,1672794064],"tags":{"bridge":"yes","highway":"tertiary","lane_markings":"yes","lanes":"2","lanes:backward":"1","lanes:forward":"1","layer":"1","lcn":"yes","lit":"no","maxspeed":"50","maxspeed:type":"sign","name":"Stevede","ref":"K 48","shoulder":"no","sidewalk":"right","surface":"asphalt","zone:traffic":"DE:rural"}},{"type":"way","id":254542430,"nodes":[2721003308,2721003086,2721003095,2721003215,2721003245,2721003339,2721003308],"tags":{"addr:city":"Reken","addr:country":"DE","addr:housenumber":"32","addr:postcode":"48734","addr:street":"Zum Heubach","addr:suburb":"Maria Veen","building":"house","disused":"yes","man_made":"watermill","name":"Brockmühle"}},{"type":"way","id":399077876,"nodes":[4018159190,4018159189],"tags":{"bridge":"yes","highway":"track","smoothness":"intermediate","surface":"paved","tracktype":"grade3"}},{"type":"way","id":916934323,"nodes":[2299490776,8516317220],"tags":{"bridge":"yes","highway":"track","layer":"1"}},{"type":"way","id":936154340,"nodes":[8674577963,297303009],"tags":{"bridge":"yes","highway":"trunk","lanes":"3","lanes:backward":"1","lanes:forward":"2","layer":"1","maxspeed":"100","motorroad":"yes","note":"2+1-System","ref":"B 67","source":"http://wiki.openstreetmap.org/wiki/Import/Catalogue/Strassen_NRW"}},{"type":"way","id":1093453355,"nodes":[10014139173,10014139174],"tags":{"bridge":"yes","construction":"trunk","highway":"construction","lanes":"3","layer":"1","opening_date":"2027-12-31","ref":"B 67n;B 474n","source":"Planfeststellung für den Neubau der Bundesstraße 67n von Bau-km 0,000 bis Bau-km 12,350 sowie für den Neubau der Bundesstraße 474n von Bau-km 12,350 bis Bau-km 15,450"}},{"type":"way","id":1093453362,"nodes":[10014139212,3555010553],"tags":{"bridge":"yes","construction":"trunk","highway":"construction","lanes":"3","layer":"1","opening_date":"2027-12-31","ref":"B 67n;B 474n","source":"Planfeststellung für den Neubau der Bundesstraße 67n von Bau-km 0,000 bis Bau-km 12,350 sowie für den Neubau der Bundesstraße 474n von Bau-km 12,350 bis Bau-km 15,450"}},{"type":"way","id":1093453364,"nodes":[10014139213,10014139216],"tags":{"bridge":"yes","construction":"trunk","highway":"construction","lanes":"3","layer":"1","opening_date":"2027-12-31","ref":"B 67n;B 474n","source":"Planfeststellung für den Neubau der Bundesstraße 67n von Bau-km 0,000 bis Bau-km 12,350 sowie für den Neubau der Bundesstraße 474n von Bau-km 12,350 bis Bau-km 15,450"}},{"type":"way","id":1210491947,"nodes":[10172232227,11883586652],"tags":{"bicycle":"yes","bridge":"yes","foot":"yes","highway":"track","layer":"1","motor_vehicle":"agricultural","mtb:scale":"0","smoothness":"intermediate","surface":"compacted","tracktype":"grade3","width":"3"}},{"type":"way","id":1329076305,"nodes":[12296594778,12296594779],"tags":{"bridge":"yes","construction":"trunk","highway":"construction","lanes":"3","layer":"1","opening_date":"2027-12-31","ref":"B 67n;B 474n","source":"Planfeststellung für den Neubau der Bundesstraße 67n von Bau-km 0,000 bis Bau-km 12,350 sowie für den Neubau der Bundesstraße 474n von Bau-km 12,350 bis Bau-km 15,450"}},{"type":"node","id":360797275,"lat":51.8510916,"lon":7.0390605},{"type":"node","id":360797277,"lat":51.8514255,"lon":7.0392241},{"type":"node","id":279851608,"lat":51.8516254,"lon":7.0498839},{"type":"node","id":279851617,"lat":51.8516731,"lon":7.050342},{"type":"node","id":102862426,"lat":51.8521918,"lon":7.0539291},{"type":"node","id":102862434,"lat":51.852289,"lon":7.0544633},{"type":"node","id":297303009,"lat":51.8539025,"lon":7.0624488},{"type":"node","id":8674577963,"lat":51.8538617,"lon":7.0622344},{"type":"node","id":2299490776,"lat":51.8662382,"lon":7.0747231},{"type":"node","id":8516317220,"lat":51.8662753,"lon":7.074876},{"type":"node","id":1672751713,"lat":51.8415111,"lon":7.1070284},{"type":"node","id":1672751731,"lat":51.8416119,"lon":7.1071516},{"type":"node","id":4018159189,"lat":51.8407486,"lon":7.1120045},{"type":"node","id":4018159190,"lat":51.8407585,"lon":7.1118293},{"type":"node","id":1672752049,"lat":51.8449116,"lon":7.1024179},{"type":"node","id":1672752061,"lat":51.8450212,"lon":7.1025002},{"type":"node","id":1672794063,"lat":51.8463694,"lon":7.0993951},{"type":"node","id":1672794064,"lat":51.8464998,"lon":7.0995812},{"type":"node","id":2721003086,"lat":51.8460291,"lon":7.099259},{"type":"node","id":2721003095,"lat":51.8460319,"lon":7.0993823},{"type":"node","id":2721003215,"lat":51.8461162,"lon":7.0993767},{"type":"node","id":2721003245,"lat":51.8461251,"lon":7.0995307},{"type":"node","id":2721003308,"lat":51.8461728,"lon":7.0992501},{"type":"node","id":2721003339,"lat":51.8461922,"lon":7.0995161},{"type":"node","id":1672769734,"lat":51.8573657,"lon":7.081827},{"type":"node","id":1672769735,"lat":51.8574331,"lon":7.0819791},{"type":"node","id":10014139173,"lat":51.8590276,"lon":7.0838503},{"type":"node","id":10014139174,"lat":51.8590875,"lon":7.0839398},{"type":"node","id":12296594778,"lat":51.8575492,"lon":7.0815752},{"type":"node","id":12296594779,"lat":51.85764,"lon":7.0817349},{"type":"node","id":295658847,"lat":51.8435296,"lon":7.1046148},{"type":"node","id":1672751916,"lat":51.8434186,"lon":7.1044602},{"type":"node","id":10172232227,"lat":51.8503637,"lon":7.1103058},{"type":"node","id":11883586652,"lat":51.8504017,"lon":7.1104188},{"type":"node","id":10014139213,"lat":51.8617808,"lon":7.1059476},{"type":"node","id":10014139216,"lat":51.8616404,"lon":7.106377},{"type":"node","id":3555010553,"lat":51.8587618,"lon":7.1130939},{"type":"node","id":10014139212,"lat":51.8588497,"lon":7.1128539}]}}
