{"query_name":"03-bridges-waterworks","query_signature":"d3dbc7f18db9c9e1143b83718b2335f6eb602dbd","tile_path":"57","payload":{"version":0.6,"generator":"Overpass API 0.7.62.11 87bfad18","osm3s":{"timestamp_osm_base":"2026-07-14T20:32:02Z","copyright":"The data included in this document is from www.openstreetmap.org. The data is made available under ODbL."},"elements":[{"type":"node","id":9791621032,"lat":51.9299491,"lon":6.5698738,"tags":{"waterway":"weir"}},{"type":"node","id":9791621048,"lat":51.9245038,"lon":6.577376,"tags":{"waterway":"weir"}},{"type":"node","id":9791621076,"lat":51.9266448,"lon":6.5897126,"tags":{"name":"Stuw 1e Haartbrug","operator":"Waterschap Rijn en IJssel","waterway":"weir"}},{"type":"node","id":10026820262,"lat":51.9078248,"lon":6.5529496,"tags":{"waterway":"weir"}},{"type":"node","id":11796038729,"lat":51.931833,"lon":6.5535244,"tags":{"waterway":"weir"}},{"type":"way","id":6307124,"nodes":[44408603,44409086],"tags":{"bridge":"yes","description":"Winterswijk - Zevenaar","electrified":"no","gauge":"1435","layer":"1","maxspeed":"100","operator":"ProRail","passenger_lines":"1","railway":"rail","railway:atb":"yes","railway:atb-ng":"yes","railway:track_class":"C2","ref":"212","usage":"branch"}},{"type":"way","id":6696924,"nodes":[7781947653,44401889],"tags":{"bridge":"yes","highway":"residential","layer":"1","maxspeed":"50","name":"Kriegerdreef"}},{"type":"way","id":6697168,"nodes":[13308017048,44397247],"tags":{"bridge":"yes","highway":"tertiary","layer":"1","lit":"yes","maxspeed":"50","maxweight:signed":"no","name":"Slaadreef"}},{"type":"way","id":6697184,"nodes":[44407755,44408165],"tags":{"bridge":"yes","highway":"unclassified","layer":"1","maxspeed":"60","name":"Loohuisweg"}},{"type":"way","id":6697224,"nodes":[44417925,44419380],"tags":{"bridge":"yes","cycleway:both":"shared_lane","cycleway:both:lane":"advisory","highway":"tertiary","lane_markings":"no","layer":"1","lit":"yes","maxspeed":"30","maxweight:signed":"no","name":"Dijkstraat","sidewalk":"both","surface":"asphalt"}},{"type":"way","id":6697260,"nodes":[44423670,44424039],"tags":{"bridge":"yes","cycleway:both":"shared_lane","cycleway:both:lane":"advisory","highway":"tertiary","lane_markings":"no","layer":"1","lit":"yes","maxspeed":"30","maxweight:signed":"no","name":"Wehmerstraat","surface":"sett"}},{"type":"way","id":6697265,"nodes":[12056259419,12056259418],"tags":{"bridge":"yes","highway":"tertiary","lane_markings":"no","layer":"1","lit":"yes","maxspeed":"30","maxweight:signed":"no","name":"Haartsestraat","surface":"paving_stones"}},{"type":"way","id":6697300,"nodes":[44426367,10051087012],"tags":{"bridge":"yes","cycleway":"shared_lane","highway":"tertiary","lane_markings":"no","layer":"1","lit":"no","maxspeed":"60","maxweight:signed":"no","name":"Haartseweg","surface":"asphalt"}},{"type":"way","id":6697306,"nodes":[44413194,44414807],"tags":{"bicycle":"no","bridge":"yes","highway":"primary","lanes":"2","layer":"1","maxspeed":"80","maxweight:signed":"no","name":"Hamelandroute","operator":"Provincie Gelderland","ref":"N313","shoulder":"no","surface":"asphalt"}},{"type":"way","id":6697312,"nodes":[44436994,44438630],"tags":{"bicycle":"no","bridge":"yes","highway":"primary","lanes":"2","layer":"1","maxspeed":"80","maxweight:signed":"no","name":"Hamelandroute","operator":"Provincie Gelderland","ref":"N313","shoulder":"no","surface":"asphalt"}},{"type":"way","id":6697315,"nodes":[44408934,44410553],"tags":{"bicycle":"no","bridge":"yes","highway":"primary","lanes":"2","layer":"1","maxspeed":"80","maxweight:signed":"no","name":"Hamelandroute","operator":"Provincie Gelderland","ref":"N313","shoulder":"no","surface":"asphalt"}},{"type":"way","id":6697331,"nodes":[44424579,44425518],"tags":{"bicycle":"no","bridge":"yes","highway":"primary","lanes":"2","layer":"1","maxspeed":"80","maxweight:signed":"no","name":"Hamelandroute","operator":"Provincie Gelderland","ref":"N313","shoulder":"no","surface":"asphalt"}},{"type":"way","id":6697552,"nodes":[44432494,44432828],"tags":{"bridge":"yes","highway":"unclassified","lane_markings":"no","layer":"1","lit":"yes","maxspeed":"30","maxweight:signed":"no","name":"Willemstraat","sidewalk":"both","surface":"paving_stones","width":"5.3"}},{"type":"way","id":6697627,"nodes":[44450205,8261333787,9786693675,44451895],"tags":{"bridge":"yes","cycleway":"lane","highway":"tertiary","layer":"1","lit":"no","maxspeed":"60","maxweight:signed":"no","name":"Aladnaweg"}},{"type":"way","id":6697681,"nodes":[44420775,44422217],"tags":{"bridge":"yes","cycleway:both":"shared_lane","cycleway:both:lane":"advisory","highway":"tertiary","lane_markings":"no","layer":"1","lit":"yes","maxspeed":"50","maxweight:signed":"no","name":"van Heemskerckstraat","sidewalk":"both","surface":"asphalt"}},{"type":"way","id":6697726,"nodes":[44446121,44446712],"tags":{"bicycle":"no","bridge":"yes","foot":"no","highway":"primary","lanes":"2","layer":"1","maxspeed":"70","maxspeed:type":"sign","maxweight:signed":"no","name":"Varsseveldsestraatweg","operator":"Provincie Gelderland","ref":"N318","shoulder":"no","surface":"asphalt","zone:traffic":"NL:rural"}},{"type":"way","id":6697909,"nodes":[44372828,44374702],"tags":{"bicycle":"no","bridge":"yes","highway":"secondary","lanes":"2","layer":"1","maxspeed":"50","name":"Bocholtsestraatweg","surface":"asphalt"}},{"type":"way","id":6697913,"nodes":[44362124,4149809339],"tags":{"bicycle":"no","bridge":"yes","bridge:name":"Piepersbrug","highway":"secondary","lanes":"2","layer":"1","maxspeed":"50","name":"Dinxperlosestraatweg","operator":"Provincie Gelderland","ref":"N819","start_date":"1950","surface":"asphalt","zone:traffic":"NL:urban"}},{"type":"way","id":6780568,"nodes":[44340188,44341139],"tags":{"bridge":"yes","highway":"unclassified","layer":"1","lit":"no","maxspeed":"60","name":"Veldweg","smoothness":"good","surface":"asphalt"}},{"type":"way","id":6781579,"nodes":[44457183,44458582],"tags":{"bridge":"yes","highway":"unclassified","layer":"1","maxspeed":"60","name":"Slatdijk"}},{"type":"way","id":43523136,"nodes":[549318705,549318707],"tags":{"bicycle":"no","bridge":"yes","highway":"unclassified","layer":"1","maxspeed":"50","name":"Rondweg Zuid"}},{"type":"way","id":46965858,"nodes":[599331647,599331646],"tags":{"bicycle":"yes","bridge":"yes","foot":"yes","highway":"path","layer":"1","lit":"no","name":"Richterinkvonder","start_date":"1936","surface":"wood"}},{"type":"way","id":60047918,"nodes":[8824662493,3561916539,44382518],"tags":{"alt_name":"The King's Company, Grenadier Guards Brug","bridge":"yes","bridge:name":"The King's Company Brug Grenadier Guards","foot":"yes","goods":"yes","highway":"cycleway","layer":"1","maxspeed":"30","moped":"yes","motor_vehicle":"no","name":"Bodendijk"}},{"type":"way","id":66474967,"nodes":[12050901159,662458521],"tags":{"bridge":"yes","disused:bridge":"yes","highway":"footway","layer":"1","lit":"no","surface":"concrete"}},{"type":"way","id":66474968,"nodes":[662458455,662458456],"tags":{"bridge":"yes","highway":"cycleway","layer":"1","lit":"yes","name":"Wehmerpad","source:width":"ARCore","surface":"metal","width":"1.2"}},{"type":"way","id":66474969,"nodes":[662458537,12050875845],"tags":{"bridge":"yes","highway":"path","layer":"1","lit":"yes","surface":"wood"}},{"type":"way","id":87178084,"nodes":[1013708325,44420835],"tags":{"bridge":"yes","highway":"residential","layer":"1","lit":"yes","maxspeed":"30","maxweight:signed":"no","name":"Stationsstraat","sidewalk":"both","source:width":"ARCore","surface":"paving_stones","width":"5.4"}},{"type":"way","id":94227526,"nodes":[1095035194,1095035424],"tags":{"bridge":"yes","description":"Winterswijk - Zevenaar","electrified":"no","gauge":"1435","layer":"1","maxspeed":"100","operator":"ProRail","passenger_lines":"1","railway":"rail","railway:atb":"yes","railway:atb-ng":"yes","railway:track_class":"C2","ref":"212","usage":"branch"}},{"type":"way","id":105185649,"nodes":[1212105635,1212105634],"tags":{"bridge":"yes","highway":"cycleway","layer":"1"}},{"type":"way","id":105189566,"nodes":[662458606,662458610],"tags":{"bridge":"yes","highway":"path","layer":"1","smoothness":"good","surface":"wood"}},{"type":"way","id":105189979,"nodes":[1212160709,1212160712],"tags":{"bridge":"yes","highway":"cycleway","layer":"1","lit":"no","mofa":"no","moped":"no","name":"Nannielaantje","segregated":"no","smoothness":"good","surface":"asphalt","traffic_sign":"NL:G13"}},{"type":"way","id":114787638,"nodes":[1260002103,1260002066],"tags":{"bridge":"yes","foot":"yes","highway":"cycleway","layer":"1","lit":"yes","mofa":"yes","moped":"no","name":"Bocholtsestraatweg","oneway":"no","segregated":"yes","sidewalk":"right","smoothness":"good","surface":"asphalt","traffic_sign":"NL:G11"}},{"type":"way","id":188340832,"nodes":[599333323,2078547581],"tags":{"agricultural":"yes","bridge":"yes","hgv":"no","highway":"track","layer":"1","maxspeed":"60","name":"Walfortlaan","smoothness":"good","surface":"concrete","tracktype":"grade1"}},{"type":"way","id":194625629,"nodes":[2051315930,1013983864],"tags":{"bicycle":"designated","bridge":"yes","foot":"designated","highway":"cycleway","layer":"1","moped":"designated","zone:traffic":"NL:urban"}},{"type":"way","id":196496279,"nodes":[2068249240,2068249235],"tags":{"bridge":"yes","highway":"path","layer":"1"}},{"type":"way","id":196496904,"nodes":[2068253766,6936703785],"tags":{"bridge":"yes","highway":"track","layer":"1"}},{"type":"way","id":196628998,"nodes":[2069364320,2069364322],"tags":{"bridge":"yes","highway":"path","layer":"1"}},{"type":"way","id":196629125,"nodes":[4741646250,2069365451],"tags":{"bridge":"yes","highway":"service","layer":"1","service":"driveway"}},{"type":"way","id":196634689,"nodes":[2069418069,2069417970],"tags":{"bridge":"yes","highway":"path","layer":"1"}},{"type":"way","id":196634701,"nodes":[2069418035,2069418072],"tags":{"bridge":"yes","highway":"path","layer":"1"}},{"type":"way","id":196634852,"nodes":[2069418051,2069425331],"tags":{"bridge":"yes","highway":"path","layer":"1"}},{"type":"way","id":197148134,"nodes":[2074405488,2069451909],"tags":{"bridge":"yes","highway":"cycleway","layer":"1","oneway":"yes","zone:traffic":"NL:urban"}},{"type":"way","id":197635908,"nodes":[2078420529,1207971657],"tags":{"bridge":"yes","foot":"yes","highway":"cycleway","layer":"1","mofa":"no","moped":"no","motor_vehicle":"no","motorcycle":"no","segregated":"no","smoothness":"good","surface":"wood","traffic_sign":"NL:G13"}},{"type":"way","id":197651775,"nodes":[2078547544,8262989907],"tags":{"agricultural":"yes","bridge":"yes","hgv":"no","highway":"track","layer":"1","maxspeed":"60","name":"Walfortlaan","surface":"asphalt","tracktype":"grade1"}},{"type":"way","id":342604693,"nodes":[3495715580,3495715589],"tags":{"bridge":"yes","foot":"yes","highway":"path","layer":"1","surface":"paving_stones"}},{"type":"way","id":342604695,"nodes":[3495715582,9791621076,3495715588],"tags":{"waterway":"weir"}},{"type":"way","id":513274608,"nodes":[5017797277,5017797278],"tags":{"bridge":"yes","highway":"footway","layer":"1","lit":"no","surface":"wood","width":"2"}},{"type":"way","id":513274611,"nodes":[5005000328,5017797282],"tags":{"bridge":"yes","highway":"footway","layer":"1"}},{"type":"way","id":740915164,"nodes":[6051426882,44424145],"tags":{"bridge":"yes","highway":"tertiary","lane_markings":"no","layer":"1","lit":"yes","maxspeed":"50","maxweight:signed":"no","name":"Polstraat","surface":"asphalt"}},{"type":"way","id":883973732,"nodes":[722736454,8221086281,722736992],"tags":{"waterway":"weir"}},{"type":"way","id":883973733,"nodes":[8221086294,8221086293,8221086292,8221086291,8221086290,8221086289,8221086288,8221086285,8221086287],"tags":{"waterway":"weir"}},{"type":"way","id":883973742,"nodes":[8221086343,8221086342,8221086341],"tags":{"waterway":"weir"}},{"type":"way","id":883973745,"nodes":[8221086355,8221086359,8221086363,590241244,8221086354],"tags":{"waterway":"weir"}},{"type":"way","id":990963087,"nodes":[9156176995,9156176996],"tags":{"bridge":"yes","highway":"path","layer":"1"}},{"type":"way","id":1097714294,"nodes":[44424579,10051064191,10051064190,10051064189,10051064188,44424579],"tags":{"bridge":"viaduct","bridge:structure":"beam","layer":"1","man_made":"bridge"}},{"type":"way","id":1098230524,"nodes":[10055707761,10055707760],"tags":{"access":"private","bridge":"yes","highway":"footway","layer":"1","smoothness":"good","surface":"wood"}},{"type":"way","id":1270432943,"nodes":[11795978061,11795978060],"tags":{"bridge":"yes","highway":"footway","layer":"1","lit":"no","surface":"fine_gravel","width":"1"}},{"type":"way","id":1270432948,"nodes":[5003015661,7614564653],"tags":{"bridge":"yes","highway":"footway","layer":"1","lit":"no","surface":"fine_gravel","width":"1"}},{"type":"way","id":1300917206,"nodes":[12049384504,12049384505],"tags":{"bridge":"yes","highway":"service","layer":"1","lit":"yes","service":"driveway"}},{"type":"way","id":1300948085,"nodes":[590071285,9791621048,12049684377],"tags":{"waterway":"weir"}},{"type":"way","id":1451038336,"nodes":[13307921278,13307921279,13307921277],"tags":{"bridge":"yes","highway":"service","layer":"1","service":"driveway"}},{"type":"node","id":44340188,"lat":51.9078192,"lon":6.5530144},{"type":"node","id":44341139,"lat":51.9078857,"lon":6.5529718},{"type":"node","id":1207971657,"lat":51.9095413,"lon":6.5590335},{"type":"node","id":2078420529,"lat":51.9096709,"lon":6.5589629},{"type":"node","id":549318705,"lat":51.9112573,"lon":6.566825},{"type":"node","id":549318707,"lat":51.911132,"lon":6.5668848},{"type":"node","id":1212105634,"lat":51.9112759,"lon":6.5669029},{"type":"node","id":1212105635,"lat":51.9111527,"lon":6.5669628},{"type":"node","id":44362124,"lat":51.9126021,"lon":6.5744392},{"type":"node","id":1013983864,"lat":51.9127102,"lon":6.5746516},{"type":"node","id":2051315930,"lat":51.9125897,"lon":6.5745528},{"type":"node","id":2069451909,"lat":51.9126386,"lon":6.5743197},{"type":"node","id":2074405488,"lat":51.9127625,"lon":6.5744173},{"type":"node","id":4149809339,"lat":51.9127215,"lon":6.574536},{"type":"node","id":13307921277,"lat":51.9136966,"lon":6.5884318},{"type":"node","id":13307921278,"lat":51.9137288,"lon":6.5885054},{"type":"node","id":13307921279,"lat":51.9137123,"lon":6.5884698},{"type":"node","id":44372828,"lat":51.9149016,"lon":6.5814782},{"type":"node","id":44374702,"lat":51.9149851,"lon":6.5814137},{"type":"node","id":44382518,"lat":51.9165207,"lon":6.5852437},{"type":"node","id":1260002066,"lat":51.9148765,"lon":6.5814033},{"type":"node","id":1260002103,"lat":51.9149627,"lon":6.5813232},{"type":"node","id":3561916539,"lat":51.9164386,"lon":6.585334},{"type":"node","id":8824662493,"lat":51.9163897,"lon":6.5853891},{"type":"node","id":2069417970,"lat":51.9166167,"lon":6.591447},{"type":"node","id":2069418035,"lat":51.9180296,"lon":6.5889273},{"type":"node","id":2069418051,"lat":51.9169241,"lon":6.5866544},{"type":"node","id":2069418069,"lat":51.9165333,"lon":6.5916846},{"type":"node","id":2069418072,"lat":51.91792,"lon":6.5890578},{"type":"node","id":2069425331,"lat":51.9170327,"lon":6.5865215},{"type":"node","id":5005000328,"lat":51.9161288,"lon":6.5887765},{"type":"node","id":5017797282,"lat":51.9159765,"lon":6.5888103},{"type":"node","id":44397247,"lat":51.9198095,"lon":6.5931801},{"type":"node","id":44401889,"lat":51.920787,"lon":6.5940346},{"type":"node","id":7781947653,"lat":51.9206964,"lon":6.5942423},{"type":"node","id":13308017048,"lat":51.9196911,"lon":6.5933092},{"type":"node","id":44457183,"lat":51.9318529,"lon":6.5531737},{"type":"node","id":44458582,"lat":51.93197,"lon":6.5533319},{"type":"node","id":44450205,"lat":51.9305199,"lon":6.5604522},{"type":"node","id":44451895,"lat":51.9308199,"lon":6.5602822},{"type":"node","id":8261333787,"lat":51.930615,"lon":6.5603983},{"type":"node","id":9786693675,"lat":51.9307885,"lon":6.5603},{"type":"node","id":44432494,"lat":51.9271341,"lon":6.5713617},{"type":"node","id":44432828,"lat":51.9271641,"lon":6.571169},{"type":"node","id":599331646,"lat":51.9260963,"lon":6.5718752},{"type":"node","id":599331647,"lat":51.9262037,"lon":6.5719615},{"type":"node","id":44420775,"lat":51.9245972,"lon":6.5742377},{"type":"node","id":44420835,"lat":51.9244916,"lon":6.5792358},{"type":"node","id":44422217,"lat":51.9247692,"lon":6.5742624},{"type":"node","id":590071285,"lat":51.9244645,"lon":6.5773496},{"type":"node","id":1013708325,"lat":51.9243875,"lon":6.5792015},{"type":"node","id":5003015661,"lat":51.9243908,"lon":6.5784541},{"type":"node","id":5017797277,"lat":51.9244726,"lon":6.5768157},{"type":"node","id":5017797278,"lat":51.9245957,"lon":6.5768077},{"type":"node","id":7614564653,"lat":51.9244393,"lon":6.5784823},{"type":"node","id":9791621048,"lat":51.9245038,"lon":6.577376},{"type":"node","id":11795978060,"lat":51.9245698,"lon":6.5775082},{"type":"node","id":11795978061,"lat":51.9246039,"lon":6.5775051},{"type":"node","id":12049684377,"lat":51.9245414,"lon":6.5773984},{"type":"node","id":44446121,"lat":51.9297983,"lon":6.5698879},{"type":"node","id":44446712,"lat":51.9298856,"lon":6.570094},{"type":"node","id":44417925,"lat":51.9241246,"lon":6.5807135},{"type":"node","id":44419380,"lat":51.9242419,"lon":6.5807617},{"type":"node","id":44423670,"lat":51.9251773,"lon":6.5814542},{"type":"node","id":44424039,"lat":51.9251977,"lon":6.5812784},{"type":"node","id":44424145,"lat":51.9251873,"lon":6.5863554},{"type":"node","id":662458455,"lat":51.9249513,"lon":6.5831968},{"type":"node","id":662458456,"lat":51.9250251,"lon":6.5831984},{"type":"node","id":662458521,"lat":51.9251274,"lon":6.5851704},{"type":"node","id":662458537,"lat":51.9251531,"lon":6.5861352},{"type":"node","id":2069365451,"lat":51.9250757,"lon":6.5827863},{"type":"node","id":4741646250,"lat":51.9249657,"lon":6.5827356},{"type":"node","id":12049384504,"lat":51.9245483,"lon":6.5811739},{"type":"node","id":12049384505,"lat":51.9245721,"lon":6.5810233},{"type":"node","id":12050875845,"lat":51.9250837,"lon":6.5861116},{"type":"node","id":12050901159,"lat":51.9250102,"lon":6.5851874},{"type":"node","id":662458606,"lat":51.9260762,"lon":6.5882678},{"type":"node","id":662458610,"lat":51.9260037,"lon":6.5885336},{"type":"node","id":3495715580,"lat":51.9265589,"lon":6.5896682},{"type":"node","id":3495715582,"lat":51.9265631,"lon":6.5897054},{"type":"node","id":3495715588,"lat":51.9267085,"lon":6.5897182},{"type":"node","id":3495715589,"lat":51.9267167,"lon":6.589696},{"type":"node","id":6051426882,"lat":51.9250934,"lon":6.5863883},{"type":"node","id":9791621076,"lat":51.9266448,"lon":6.5897126},{"type":"node","id":12056259418,"lat":51.9266731,"lon":6.5888024},{"type":"node","id":12056259419,"lat":51.9266134,"lon":6.5889148},{"type":"node","id":44407755,"lat":51.9220512,"lon":6.5946182},{"type":"node","id":44408165,"lat":51.922142,"lon":6.5949855},{"type":"node","id":44408603,"lat":51.922251,"lon":6.5946553},{"type":"node","id":44408934,"lat":51.9223067,"lon":6.5986288},{"type":"node","id":44409086,"lat":51.9223611,"lon":6.595121},{"type":"node","id":44410553,"lat":51.9226117,"lon":6.5987334},{"type":"node","id":44413194,"lat":51.9231317,"lon":6.5989134},{"type":"node","id":44414807,"lat":51.9234617,"lon":6.5990288},{"type":"node","id":2068249235,"lat":51.9244733,"lon":6.5987832},{"type":"node","id":2068249240,"lat":51.9243357,"lon":6.5988233},{"type":"node","id":2068253766,"lat":51.9234498,"lon":6.5951883},{"type":"node","id":6936703785,"lat":51.9234571,"lon":6.5949431},{"type":"node","id":44424579,"lat":51.9253843,"lon":6.5997032},{"type":"node","id":44425518,"lat":51.9255295,"lon":6.5997509},{"type":"node","id":44426367,"lat":51.92573,"lon":6.6029797},{"type":"node","id":590241244,"lat":51.9262071,"lon":6.6028943},{"type":"node","id":8221086341,"lat":51.9259516,"lon":6.6059449},{"type":"node","id":8221086342,"lat":51.9259867,"lon":6.6059633},{"type":"node","id":8221086343,"lat":51.9260269,"lon":6.6059845},{"type":"node","id":8221086354,"lat":51.9261712,"lon":6.6029027},{"type":"node","id":8221086355,"lat":51.9262831,"lon":6.6028716},{"type":"node","id":8221086359,"lat":51.9262544,"lon":6.6028811},{"type":"node","id":8221086363,"lat":51.9262326,"lon":6.602888},{"type":"node","id":9156176995,"lat":51.9261714,"lon":6.6029124},{"type":"node","id":9156176996,"lat":51.9262831,"lon":6.6028783},{"type":"node","id":10051064188,"lat":51.9253871,"lon":6.5996018},{"type":"node","id":10051064189,"lat":51.9255371,"lon":6.5996575},{"type":"node","id":10051064190,"lat":51.9255174,"lon":6.5998584},{"type":"node","id":10051064191,"lat":51.9253842,"lon":6.5998122},{"type":"node","id":10051087012,"lat":51.9257302,"lon":6.6028069},{"type":"node","id":1212160709,"lat":51.9278077,"lon":6.596162},{"type":"node","id":1212160712,"lat":51.927993,"lon":6.5960532},{"type":"node","id":44436994,"lat":51.9279696,"lon":6.6005518},{"type":"node","id":44438630,"lat":51.9282865,"lon":6.6006116},{"type":"node","id":2069364320,"lat":51.9280017,"lon":6.6002013},{"type":"node","id":2069364322,"lat":51.9282541,"lon":6.6001763},{"type":"node","id":1095035194,"lat":51.9251984,"lon":6.607107},{"type":"node","id":1095035424,"lat":51.9252292,"lon":6.6072328},{"type":"node","id":10055707760,"lat":51.9211464,"lon":6.6142379},{"type":"node","id":10055707761,"lat":51.921236,"lon":6.614271},{"type":"node","id":599333323,"lat":51.9339935,"lon":6.6084466},{"type":"node","id":2078547544,"lat":51.9338724,"lon":6.608924},{"type":"node","id":2078547581,"lat":51.9339112,"lon":6.6087749},{"type":"node","id":8262989907,"lat":51.9338074,"lon":6.609193},{"type":"node","id":722736454,"lat":51.9250284,"lon":6.6235826},{"type":"node","id":722736992,"lat":51.9249796,"lon":6.6235528},{"type":"node","id":8221086281,"lat":51.9250161,"lon":6.623576},{"type":"node","id":8221086285,"lat":51.9248795,"lon":6.6244077},{"type":"node","id":8221086287,"lat":51.9248819,"lon":6.6244134},{"type":"node","id":8221086288,"lat":51.9248756,"lon":6.6244008},{"type":"node","id":8221086289,"lat":51.924871,"lon":6.6243954},{"type":"node","id":8221086290,"lat":51.924867,"lon":6.6243909},{"type":"node","id":8221086291,"lat":51.9248617,"lon":6.6243876},{"type":"node","id":8221086292,"lat":51.9248553,"lon":6.6243855},{"type":"node","id":8221086293,"lat":51.9248484,"lon":6.6243843},{"type":"node","id":8221086294,"lat":51.9248401,"lon":6.6243851}]}}
