{"query_name":"06-settlements","query_signature":"d63820c79883476e3a40ab2030d1354438c0e692","tile_path":"154","payload":{"version":0.6,"generator":"Overpass API 0.7.62.11 87bfad18","osm3s":{"timestamp_osm_base":"2026-07-14T17:42:04Z","copyright":"The data included in this document is from www.openstreetmap.org. The data is made available under ODbL."},"elements":[{"type":"node","id":45296730,"lat":52.1127593,"lon":6.6590935,"tags":{"name":"Mallem","place":"hamlet","postal_code":"7151","source":"AND"}},{"type":"node","id":45435505,"lat":52.1405464,"lon":6.6625951,"tags":{"name":"Rietmolen","name:carnaval":"Kwakersdorp","place":"village","population":"1035","population:date":"2017-01-01","postal_code":"7165","source:population":"https://berkelland.incijfers.nl/jive","wikidata":"Q2539168"}}]}}
