{"query_name":"04-places-heritage","query_signature":"6bd4cc82f374ec1272a1a678f8330cf822348234","tile_path":"16","payload":{"version":0.6,"generator":"Overpass API 0.7.62.11 87bfad18","osm3s":{"timestamp_osm_base":"2026-07-14T21:24:08Z","copyright":"The data included in this document is from www.openstreetmap.org. The data is made available under ODbL."},"elements":[{"type":"node","id":4949506670,"lat":51.8296318,"lon":7.1412126,"tags":{"denomination":"roman_catholic","description":"Mosaik Hl. Antonius","historic":"wayside_shrine","inscription":"AD 1961","material":"brick","name":"Antoniusbildstock","religion":"christian"}},{"type":"node","id":8567209412,"lat":51.8039303,"lon":7.1337615,"tags":{"archaeological_site":"tumulus","description":"Haltern Bodendenkmal Nr. 6, MKZ 4108,8","historic":"archaeological_site"}},{"type":"way","id":531006039,"nodes":[5155076497,5155076505,5155076503,5155076498,5155076499,8888853244,8888853243,8888853242,5155076500,5155076504,5155076501,5155076502,5155076497],"tags":{"archaeological_site":"tumulus","field":"yes","historic":"archaeological_site","historic:civilization":"germanic","historic:period":"bronze-age","name":"Kreisgrabenfriedhof auf dem Radberg","website":"https://www.lwl.org/pressemitteilungen/nr_mitteilung.php?urlID=15787","wikipedia":"de:Grabhügel auf dem Radberg"}},{"type":"node","id":5155076497,"lat":51.8086622,"lon":7.1155744},{"type":"node","id":5155076498,"lat":51.8074907,"lon":7.1166158},{"type":"node","id":5155076499,"lat":51.8073645,"lon":7.1171751},{"type":"node","id":5155076501,"lat":51.8086701,"lon":7.1167663},{"type":"node","id":5155076502,"lat":51.8090983,"lon":7.1160806},{"type":"node","id":5155076503,"lat":51.8079395,"lon":7.1153335},{"type":"node","id":5155076504,"lat":51.8085119,"lon":7.1171699},{"type":"node","id":5155076505,"lat":51.8082962,"lon":7.1152962},{"type":"node","id":5155076500,"lat":51.8082181,"lon":7.1177957},{"type":"node","id":8888853242,"lat":51.8079443,"lon":7.1183925},{"type":"node","id":8888853243,"lat":51.8077252,"lon":7.1188543},{"type":"node","id":8888853244,"lat":51.8073113,"lon":7.1176921}]}}
