{"query_name":"04-places-heritage","query_signature":"0e5d7c195ff27748de99c3d96faae8c8bbf25320","tile_path":"250","payload":{"version":0.6,"generator":"Overpass API 0.7.62.11 87bfad18","osm3s":{"timestamp_osm_base":"2026-07-14T22:21:01Z","copyright":"The data included in this document is from www.openstreetmap.org. The data is made available under ODbL."},"elements":[{"type":"node","id":2226860666,"lat":52.34771,"lon":6.6943341,"tags":{"depth":"0.10 m","description":"Het verzetsmonument in Almelo werd opgericht ter nagedachtenis aan de gebroeders Albertus en Johannes Kamphuis die hier tijdens de Tweede Wereldoorlog door de bezetter werden gefusilleerd.","height":"2 m","historic":"memorial","historic:period":"1940 - 1945","inscription":"‘HIER WERDEN 1 APRIL 1945 GEFUSILLEERD  ALBERTUS JOHANNES KAMPHUIS GEB.: 19-1-1915 TE VRIEZENVEEN JOHANNES KAMPHUIS GEB.: 17-1-1912 TE VRIEZENVEEN.  ZIJ STREDEN STEEDS HUN STRIJD MET BLIJHEID, OM TE HERWINNEN NEERLANDS VRIJHEID, ALS HELDEN VIELEN ZIJ DOOR","material":"wood","memorial":"cross","memorial:conflict":"WW2","name":"Verzetsmonument","source:website":"https://www.4en5mei.nl/oorlogsmonumenten/zoeken/2585/almelo-verzetsmonument","war_memorial":"yes","width":"1.50 m"}},{"type":"node","id":2791467310,"lat":52.3496818,"lon":6.6686705,"tags":{"historic":"memorial","memorial":"war_memorial","name":"Monument voor de Gevallenen"}},{"type":"node","id":2955655488,"lat":52.3475669,"lon":6.6944837,"tags":{"access":"private","fixme":"Van de V1 startbaan? Die lag hier wel in de buurt.","historic":"ruins"}},{"type":"node","id":2955656155,"lat":52.3314508,"lon":6.6814933,"tags":{"historic":"ruins","historic:civilization":"modern","name":"V1-lanceerinrichting"}},{"type":"node","id":2955656610,"lat":52.3279627,"lon":6.6844491,"tags":{"historic":"ruins"}},{"type":"node","id":12740889484,"lat":52.3245385,"lon":6.7088098,"tags":{"access":"yes","description":"Flying officer. Enige (?) overlevende van vliegtuigcrash in Bergentheim. Makkers begraven te Hardenberg. Op onderduikadres verraden. Gefusilleerd op de Vloedbelt bij Zenderen. Begraven te Almelo.","historic":"memorial","material":"stone","memorial":"war_memorial","memorial:conflict":"WW2","name":"Gerald Hood"}},{"type":"node","id":12740889485,"lat":52.3245529,"lon":6.7088023,"tags":{"access":"yes","description":"Nijverdalse verzetsstrijder. Op onderduikadres verraden. Gefusilleerd op de Vloedbelt bij Zenderen.","historic":"memorial","material":"stone","memorial":"war_memorial","memorial:conflict":"WW2","name":"Bote van der Wal"}},{"type":"way","id":290791066,"nodes":[2942969937,2942969942,2942969915,2942969913,2942969937],"tags":{"building":"yes","historic":"yes","ref:bag":"0141100000006698","source":"BAG","source:date":"2019-11-10","start_date":"1910"}},{"type":"node","id":2942969913,"lat":52.347253,"lon":6.6402913},{"type":"node","id":2942969915,"lat":52.3472601,"lon":6.6403717},{"type":"node","id":2942969937,"lat":52.3473029,"lon":6.6402765},{"type":"node","id":2942969942,"lat":52.3473101,"lon":6.640357}]}}
